nornir_jsonrpc/.nornir.meta
nornir_jsonrpc/__init__.py
nornir_jsonrpc/connection.py
nornir_jsonrpc/py.typed
nornir_jsonrpc/tasks.py
nornir_jsonrpc/types.py
nornir_jsonrpc-0.2.13.dist-info/METADATA
nornir_jsonrpc-0.2.13.dist-info/WHEEL
nornir_jsonrpc-0.2.13.dist-info/licenses/LICENSE
nornir_jsonrpc-0.2.13.dist-info/RECORD
