Metadata-Version: 2.4
Name: nornir-jsonrpc
Version: 0.2.13
Summary: Nornir connection plugin for the JSON RPC protocol
Project-URL: Repository, https://github.com/dgethings/nornir_jsonrpc/
Author-email: David Gethings <dgethings@me.com>
License: MIT License
License-File: LICENSE
Keywords: jsonrpc,nornir
Classifier: Development Status :: 4 - Beta
Classifier: Framework :: Pydantic :: 2
Classifier: Framework :: Pytest
Classifier: Intended Audience :: Developers
Classifier: License :: OSI Approved :: MIT License
Classifier: Operating System :: OS Independent
Classifier: Programming Language :: Python :: 3.11
Classifier: Programming Language :: Python :: 3.12
Classifier: Programming Language :: Python :: 3.13
Classifier: Topic :: System :: Networking
Classifier: Typing :: Typed
Requires-Python: >=3.11
Requires-Dist: httpx>=0.28.1
Requires-Dist: nornir>=3.5.0
Requires-Dist: pydantic>=2.10.6
Provides-Extra: build
Requires-Dist: uv~=0.7.19; extra == 'build'
